kpireport_table/__init__.py
kpireport_table/table.py
kpireport_table-0.0.1.dist-info/METADATA
kpireport_table-0.0.1.dist-info/WHEEL
kpireport_table-0.0.1.dist-info/entry_points.txt
kpireport_table-0.0.1.dist-info/top_level.txt
kpireport_table-0.0.1.dist-info/RECORD
