Metadata-Version: 2.1
Name: kpireport-table
Version: 0.0.1
Summary: UNKNOWN
Home-page: UNKNOWN
Author: KPI Reporter LLC
Author-email: dev@kpireporter.com
License: Prosperity Public License
Platform: UNKNOWN
Requires-Dist: kpireport
Requires-Dist: tabulate
